excelextractor/__init__.py
excelextractor/excelextractor.py
excelextractor-0.1.0.dist-info/WHEEL
excelextractor-0.1.0.dist-info/METADATA
excelextractor-0.1.0.dist-info/RECORD
