Metadata-Version: 2.1
Name: excelextractor
Version: 0.1.0
Summary: ExcelExtractor is an module to handle Excel documents in a normal table format for python
Home-page: https://github.com/dcfSec/SecurityRatConnector
License: Apache-2.0
Author: dcfSec
Author-email: contributor@dcfsec.com
Requires-Python: >=3.8,<4.0
Classifier: License :: OSI Approved :: Apache Software License
Classifier: Programming Language :: Python :: 3
Classifier: Programming Language :: Python :: 3.8
Classifier: Programming Language :: Python :: 3.9
Classifier: Programming Language :: Python :: 3.10
Classifier: Programming Language :: Python :: 3.11
Requires-Dist: openpyxl (>=3.0.10,<4.0.0)
Project-URL: Repository, https://github.com/dcfSec/SecurityRatConnector
